llm_devtale/__init__.py
llm_devtale/config.py
llm_devtale/files.py
llm_devtale/gitutils.py
llm_devtale/main.py
llm_devtale/node.py
llm_devtale/parser.py
llm_devtale/templates.py
llm_devtale/utils.py
llm_devtale-0.2.3.dist-info/WHEEL
llm_devtale-0.2.3.dist-info/entry_points.txt
llm_devtale-0.2.3.dist-info/METADATA
llm_devtale-0.2.3.dist-info/RECORD
