Metadata-Version: 2.3
Name: llm-devtale
Version: 0.2.3
Summary: LLM plugin to create a hierarchical summary description of a project
Author: Javier Vela
Author-email: Javier Vela <jvdiago@dagorlad.es>
License: Apache-2.0
Requires-Dist: click>=8.2.1
Requires-Dist: gitpython>=3.1.44
Requires-Dist: llm>=0.26
Requires-Dist: rich>=14.0.0
Requires-Dist: tiktoken>=0.9.0
Requires-Python: >=3.12
Project-URL: Repository, https://github.com/jvdiago/llm_devtale
